
<block_set xmlns="http://de.fhg.iais.roberta.blockly" robottype="ev3" xmlversion="2.0" description="" tags="">
	<instance x="370" y="50">
		<block type="robControls_start" id="+LH/W%-u#6Y]TAHS%XV#" intask="true" deletable="false">
			<mutation declare="true"></mutation>
			<field name="DEBUG">FALSE</field>
			<statement name="ST">
				<block type="robGlobalVariables_declare" id="?V6YQB~,=7F[FqaZ0oWa" intask="true" deletable="false" movable="false">
					<mutation next="false" declaration_type="Number"></mutation>
					<field name="VAR">s</field>
					<field name="TYPE">Number</field>
					<value name="VALUE">
						<block type="math_number" id="mjrg,)2v`h`h)_5i*WFx" intask="true">
							<field name="NUM">0</field>
						</block>
					</value>
				</block>
			</statement>
		</block>
		<block type="robControls_for" id="20m;xNko|l@}:9I)sZ1a" intask="true">
			<field name="VAR">i</field>
			<value name="FROM">
				<block type="math_number" id="F~(of+?.}7;r.RLM9)me" intask="true">
					<field name="NUM">1</field>
				</block>
			</value>
			<value name="TO">
				<block type="math_number" id="P^d}YJS)%10(cIkXm7k/" intask="true">
					<field name="NUM">3</field>
				</block>
			</value>
			<value name="BY">
				<block type="math_number" id="P(LJC3pf1e:8K`E;^OZm" intask="true">
					<field name="NUM">1</field>
				</block>
			</value>
			<statement name="DO">
				<block type="robControls_for" id="e+6cci*l7Jea?@z:Qpvo" intask="true">
					<field name="VAR">j</field>
					<value name="FROM">
						<block type="math_number" id=";5!w7^tjo2yf6Q^I(}zw" intask="true">
							<field name="NUM">1</field>
						</block>
					</value>
					<value name="TO">
						<block type="math_number" id="JZ,hs:UhY_GlZ:.|2w*A" intask="true">
							<field name="NUM">3</field>
						</block>
					</value>
					<value name="BY">
						<block type="math_number" id="yodryC070~wnl/}(6q8s" intask="true">
							<field name="NUM">1</field>
						</block>
					</value>
					<statement name="DO">
						<block type="robControls_for" id="fIZj_~rPbCp3Coon2ayx" intask="true">
							<field name="VAR">k</field>
							<value name="FROM">
								<block type="math_number" id="lX_{Vvi9jGJ`{A,RL01E" intask="true">
									<field name="NUM">1</field>
								</block>
							</value>
							<value name="TO">
								<block type="math_number" id="|2Cl+sbfGbxQgm;XO.Vc" intask="true">
									<field name="NUM">3</field>
								</block>
							</value>
							<value name="BY">
								<block type="math_number" id="9]~l.Y(YXxh/=PAFO9_-" intask="true">
									<field name="NUM">1</field>
								</block>
							</value>
							<statement name="DO">
								<block type="variables_set" id="?yTYB]6644Hn0HdKW[io" intask="true">
									<mutation datatype="Number"></mutation>
									<field name="VAR">s</field>
									<value name="VALUE">
										<block type="math_arithmetic" id="c8odQbBhH?t;|v=#R|t0" intask="true">
											<field name="OP">ADD</field>
											<value name="A">
												<block type="variables_get" id="rhM?_M3*4#p5A%;D~t}=" intask="true">
													<mutation datatype="Number"></mutation>
													<field name="VAR">i</field>
												</block>
											</value>
											<value name="B">
												<block type="math_arithmetic" id="`/UQ?U%[@@lvZ~iQr#H:" intask="true">
													<field name="OP">ADD</field>
													<value name="A">
														<block type="variables_get" id="wY7UpZsp(KIa?qTU]7BO" intask="true">
															<mutation datatype="Number"></mutation>
															<field name="VAR">j</field>
														</block>
													</value>
													<value name="B">
														<block type="variables_get" id="I#%0s%?`M[fYaI{7_2}#" intask="true">
															<mutation datatype="Number"></mutation>
															<field name="VAR">k</field>
														</block>
													</value>
												</block>
											</value>
										</block>
									</value>
								</block>
								<block type="robActions_display_text" id="TV4a_IwK%[nn{~tVTUp." intask="true">
									<value name="OUT">
										<block type="variables_get" id="l+bw7b)0y~p1w*tT[WZD" intask="true">
											<mutation datatype="Number"></mutation>
											<field name="VAR">s</field>
										</block>
									</value>
									<value name="COL">
										<block type="variables_get" id="153`YSp7qV#]W=Tme2w4" intask="true">
											<mutation datatype="Number"></mutation>
											<field name="VAR">i</field>
										</block>
									</value>
									<value name="ROW">
										<block type="variables_get" id="73lWJDgE}Rv3!,)WDI0Q" intask="true">
											<mutation datatype="Number"></mutation>
											<field name="VAR">j</field>
										</block>
									</value>
								</block>
							</statement>
						</block>
					</statement>
				</block>
			</statement>
		</block>
	</instance>
</block_set>