<block_set xmlns="http://de.fhg.iais.roberta.blockly" robottype="spike" xmlversion="" description="" tags="">
    <instance x="70" y="103">
        <block type="robConf_differentialdrive" id="AM=n{?7R#nO#1~?a3j~u" intask="true">
            <field name="NAME">_D</field>
            <field name="BRICK_WHEEL_DIAMETER">5.6</field>
            <field name="BRICK_TRACK_WIDTH">11.5</field>
            <field name="MOTOR_L">A</field>
            <field name="MOTOR_R">B</field>
        </block>
    </instance>
    <instance x="289" y="183">
        <block type="robConf_robot" id="robot" intask="true">
            <field name="ROBOT">undefined</field>
        </block>
    </instance>
    <instance x="560" y="216">
        <block type="robConf_gyro" id="}O,nU9g2cL:S*jCf~_Z*" intask="true">
            <field name="NAME">_K</field>
        </block>
    </instance>
    <instance x="143" y="251">
        <block type="robConf_motor" id="`CW3f_/xL#;Z!)*[EZz@" intask="true">
            <field name="NAME">MA</field>
            <field name="PORT">A</field>
        </block>
    </instance>
    <instance x="560" y="252">
        <block type="robConf_motor" id="S(Xm/UHHH;N[4Km1TML0" intask="true">
            <field name="NAME">MB</field>
            <field name="PORT">B</field>
        </block>
    </instance>
    <instance x="119" y="314">
        <block type="robConf_colour" id="e^*dGK},@+!mbUm6.p:-" intask="true">
            <field name="NAME">F</field>
            <field name="PORT">C</field>
        </block>
    </instance>
    <instance x="560" y="315">
        <block type="robConf_ultrasonic" id="Z5a?AUX(BKNfDVeH/-Dz" intask="true">
            <field name="NAME">U</field>
            <field name="PORT">D</field>
        </block>
    </instance>
    <instance x="144" y="373">
        <block type="robConf_display" id="tt" intask="true" deletable="false">
            <field name="NAME">_B</field>
        </block>
    </instance>
    <instance x="560" y="377">
        <block type="robConf_touch" id="BK+JQtM]!+,YDt)K-{]*" intask="true">
            <field name="NAME">B</field>
            <field name="PORT">F</field>
        </block>
    </instance>
    <instance x="136" y="440">
        <block type="robConf_key" id="](;J)ShyJ;~HcwPOpoZQ" intask="true" deletable="false">
            <field name="NAME">links</field>
            <field name="PIN1">LEFT</field>
        </block>
    </instance>
    <instance x="560" y="438">
        <block type="robConf_key" id="aCW;Mk]1|#;zP8{)Ax*;" intask="true" deletable="false">
            <field name="NAME">rechts</field>
            <field name="PIN1">RIGHT</field>
        </block>
    </instance>
    <instance x="560" y="495">
        <block type="robConf_rgbled" id="C8/{!k%9L]YDK@vW/y,h" intask="true" deletable="false">
            <field name="NAME">_R</field>
        </block>
    </instance>
    <instance x="153" y="522">
        <block type="robConf_buzzer" id="W3:Yn.C(/356snBah3a:" intask="true" deletable="false">
            <field name="NAME">_S</field>
        </block>
    </instance>
</block_set>